pymocklib/__init__.py
pymocklib/__main__.py
pymocklib/helpers.py
pymocklib/styles.py
pymocklib/transformers.py
pymocklib-1.1.3.dist-info/METADATA
pymocklib-1.1.3.dist-info/WHEEL
pymocklib-1.1.3.dist-info/RECORD
