Metadata-Version: 2.1
Name: pymocklib
Version: 1.1.3
Summary: A PYthON 3.10 lib thaT will MAkE you APpEAR WEaK ANd BUTT-HUrT on THe inTeRNET
License: MIT
Author: Alexander Bartolomey
Author-email: github@alexanderbartolomey.de
Requires-Python: >=3.10,<4.0
Classifier: License :: OSI Approved :: MIT License
Classifier: Programming Language :: Python :: 3
Classifier: Programming Language :: Python :: 3.10
Classifier: Programming Language :: Python :: 3.11
Classifier: Programming Language :: Python :: 3.12
